savannahcrm/__init__.py
savannahcrm_client-0.1.dist-info/METADATA
savannahcrm_client-0.1.dist-info/WHEEL
savannahcrm_client-0.1.dist-info/top_level.txt
savannahcrm_client-0.1.dist-info/RECORD
