Metadata-Version: 2.1
Name: savannahcrm-client
Version: 0.1
Summary: A client library for Savannah CRM
Home-page: https://github.com/SavannahHQ/savannahcrm-client-python
Author: Michael Hall
Author-email: info@savannahhq.com
License: UNKNOWN
Platform: UNKNOWN
Classifier: Programming Language :: Python :: 3
Classifier: License :: OSI Approved :: BSD License
Classifier: Operating System :: OS Independent
Requires-Python: >=3.6
Requires-Dist: requests
